{
  "build": "py36h27cfd23_1",
  "build_number": 1,
  "channel": "https://repo.anaconda.com/pkgs/main/linux-64",
  "constrains": [],
  "depends": [
    "libgcc-ng >=7.3.0",
    "python >=3.6,<3.7.0a0",
    "yaml >=0.2.5,<0.3.0a0"
  ],
  "extracted_package_dir": "/home/chparada/anaconda3/pkgs/pyyaml-5.4.1-py36h27cfd23_1",
  "features": "",
  "files": [
    "lib/python3.6/site-packages/PyYAML-5.4.1-py3.6-linux-x86_64.egg-info/PKG-INFO",
    "lib/python3.6/site-packages/PyYAML-5.4.1-py3.6-linux-x86_64.egg-info/SOURCES.txt",
    "lib/python3.6/site-packages/PyYAML-5.4.1-py3.6-linux-x86_64.egg-info/dependency_links.txt",
    "lib/python3.6/site-packages/PyYAML-5.4.1-py3.6-linux-x86_64.egg-info/native_libs.txt",
    "lib/python3.6/site-packages/PyYAML-5.4.1-py3.6-linux-x86_64.egg-info/not-zip-safe",
    "lib/python3.6/site-packages/PyYAML-5.4.1-py3.6-linux-x86_64.egg-info/top_level.txt",
    "lib/python3.6/site-packages/_yaml/__init__.py",
    "lib/python3.6/site-packages/_yaml/__pycache__/__init__.cpython-36.pyc",
    "lib/python3.6/site-packages/yaml/__init__.py",
    "lib/python3.6/site-packages/yaml/__pycache__/__init__.cpython-36.pyc",
    "lib/python3.6/site-packages/yaml/__pycache__/_yaml.cpython-36.pyc",
    "lib/python3.6/site-packages/yaml/__pycache__/composer.cpython-36.pyc",
    "lib/python3.6/site-packages/yaml/__pycache__/constructor.cpython-36.pyc",
    "lib/python3.6/site-packages/yaml/__pycache__/cyaml.cpython-36.pyc",
    "lib/python3.6/site-packages/yaml/__pycache__/dumper.cpython-36.pyc",
    "lib/python3.6/site-packages/yaml/__pycache__/emitter.cpython-36.pyc",
    "lib/python3.6/site-packages/yaml/__pycache__/error.cpython-36.pyc",
    "lib/python3.6/site-packages/yaml/__pycache__/events.cpython-36.pyc",
    "lib/python3.6/site-packages/yaml/__pycache__/loader.cpython-36.pyc",
    "lib/python3.6/site-packages/yaml/__pycache__/nodes.cpython-36.pyc",
    "lib/python3.6/site-packages/yaml/__pycache__/parser.cpython-36.pyc",
    "lib/python3.6/site-packages/yaml/__pycache__/reader.cpython-36.pyc",
    "lib/python3.6/site-packages/yaml/__pycache__/representer.cpython-36.pyc",
    "lib/python3.6/site-packages/yaml/__pycache__/resolver.cpython-36.pyc",
    "lib/python3.6/site-packages/yaml/__pycache__/scanner.cpython-36.pyc",
    "lib/python3.6/site-packages/yaml/__pycache__/serializer.cpython-36.pyc",
    "lib/python3.6/site-packages/yaml/__pycache__/tokens.cpython-36.pyc",
    "lib/python3.6/site-packages/yaml/_yaml.cpython-36m-x86_64-linux-gnu.so",
    "lib/python3.6/site-packages/yaml/_yaml.py",
    "lib/python3.6/site-packages/yaml/composer.py",
    "lib/python3.6/site-packages/yaml/constructor.py",
    "lib/python3.6/site-packages/yaml/cyaml.py",
    "lib/python3.6/site-packages/yaml/dumper.py",
    "lib/python3.6/site-packages/yaml/emitter.py",
    "lib/python3.6/site-packages/yaml/error.py",
    "lib/python3.6/site-packages/yaml/events.py",
    "lib/python3.6/site-packages/yaml/loader.py",
    "lib/python3.6/site-packages/yaml/nodes.py",
    "lib/python3.6/site-packages/yaml/parser.py",
    "lib/python3.6/site-packages/yaml/reader.py",
    "lib/python3.6/site-packages/yaml/representer.py",
    "lib/python3.6/site-packages/yaml/resolver.py",
    "lib/python3.6/site-packages/yaml/scanner.py",
    "lib/python3.6/site-packages/yaml/serializer.py",
    "lib/python3.6/site-packages/yaml/tokens.py"
  ],
  "fn": "pyyaml-5.4.1-py36h27cfd23_1.conda",
  "legacy_bz2_md5": "b708d54d1df8c1141b770b67eddeb4fc",
  "legacy_bz2_size": 179665,
  "license": "MIT",
  "license_family": "MIT",
  "link": {
    "source": "/home/chparada/anaconda3/pkgs/pyyaml-5.4.1-py36h27cfd23_1",
    "type": 1
  },
  "md5": "d502fe9b4b9157f8d0502f476d17d1e9",
  "name": "pyyaml",
  "package_tarball_full_path": "/home/chparada/anaconda3/pkgs/pyyaml-5.4.1-py36h27cfd23_1.conda",
  "paths_data": {
    "paths": [
      {
        "_path": "lib/python3.6/site-packages/PyYAML-5.4.1-py3.6-linux-x86_64.egg-info/PKG-INFO",
        "path_type": "hardlink",
        "sha256": "2d12e766540a340887a18d0cc17668e1cff7fec9bc12f95f258897b483a8ae87",
        "sha256_in_prefix": "2d12e766540a340887a18d0cc17668e1cff7fec9bc12f95f258897b483a8ae87",
        "size_in_bytes": 2178
      },
      {
        "_path": "lib/python3.6/site-packages/PyYAML-5.4.1-py3.6-linux-x86_64.egg-info/SOURCES.txt",
        "path_type": "hardlink",
        "sha256": "13946ac43c91ca0fd2021f362e1a6d2d27592a9b65d872d75032659ce787acea",
        "sha256_in_prefix": "13946ac43c91ca0fd2021f362e1a6d2d27592a9b65d872d75032659ce787acea",
        "size_in_bytes": 22195
      },
      {
        "_path": "lib/python3.6/site-packages/PyYAML-5.4.1-py3.6-linux-x86_64.egg-info/dependency_links.txt",
        "path_type": "hardlink",
        "sha256": "01ba4719c80b6fe911b091a7c05124b64eeece964e09c058ef8f9805daca546b",
        "sha256_in_prefix": "01ba4719c80b6fe911b091a7c05124b64eeece964e09c058ef8f9805daca546b",
        "size_in_bytes": 1
      },
      {
        "_path": "lib/python3.6/site-packages/PyYAML-5.4.1-py3.6-linux-x86_64.egg-info/native_libs.txt",
        "path_type": "hardlink",
        "sha256": "a38f05cb51231c93b404c0bbf8eb1983f94bdbff63a9ae6c15a3858bb79e0040",
        "sha256_in_prefix": "a38f05cb51231c93b404c0bbf8eb1983f94bdbff63a9ae6c15a3858bb79e0040",
        "size_in_bytes": 43
      },
      {
        "_path": "lib/python3.6/site-packages/PyYAML-5.4.1-py3.6-linux-x86_64.egg-info/not-zip-safe",
        "path_type": "hardlink",
        "sha256": "01ba4719c80b6fe911b091a7c05124b64eeece964e09c058ef8f9805daca546b",
        "sha256_in_prefix": "01ba4719c80b6fe911b091a7c05124b64eeece964e09c058ef8f9805daca546b",
        "size_in_bytes": 1
      },
      {
        "_path": "lib/python3.6/site-packages/PyYAML-5.4.1-py3.6-linux-x86_64.egg-info/top_level.txt",
        "path_type": "hardlink",
        "sha256": "ae98f42153138ac02387fd6f1b709c7fdbf98e9090c00cfa703d48554e597614",
        "sha256_in_prefix": "ae98f42153138ac02387fd6f1b709c7fdbf98e9090c00cfa703d48554e597614",
        "size_in_bytes": 11
      },
      {
        "_path": "lib/python3.6/site-packages/_yaml/__init__.py",
        "path_type": "hardlink",
        "sha256": "d3801eff9a2cc5a8692476b75c165401fe308ba5d7df6811f03e97ea9eb81840",
        "sha256_in_prefix": "d3801eff9a2cc5a8692476b75c165401fe308ba5d7df6811f03e97ea9eb81840",
        "size_in_bytes": 1402
      },
      {
        "_path": "lib/python3.6/site-packages/_yaml/__pycache__/__init__.cpython-36.pyc",
        "path_type": "hardlink",
        "sha256": "a415fb6b0bc4fc0d8d1044f79e0d1d5dd063670c9d9a52ab6ad8a42182f8d7b4",
        "sha256_in_prefix": "a415fb6b0bc4fc0d8d1044f79e0d1d5dd063670c9d9a52ab6ad8a42182f8d7b4",
        "size_in_bytes": 736
      },
      {
        "_path": "lib/python3.6/site-packages/yaml/__init__.py",
        "path_type": "hardlink",
        "sha256": "81fa7609b4558739278219228890f697a674a48fa6bff8991cf489e1a8f4fa76",
        "sha256_in_prefix": "81fa7609b4558739278219228890f697a674a48fa6bff8991cf489e1a8f4fa76",
        "size_in_bytes": 13170
      },
      {
        "_path": "lib/python3.6/site-packages/yaml/__pycache__/__init__.cpython-36.pyc",
        "path_type": "hardlink",
        "sha256": "a58ea5cb0b04971e3f4bf5ed116a98886e1b1ee7dc5ccd9fa51592fa7939b52b",
        "sha256_in_prefix": "a58ea5cb0b04971e3f4bf5ed116a98886e1b1ee7dc5ccd9fa51592fa7939b52b",
        "size_in_bytes": 11758
      },
      {
        "_path": "lib/python3.6/site-packages/yaml/__pycache__/_yaml.cpython-36.pyc",
        "path_type": "hardlink",
        "sha256": "4311ec3170d832b72293da5d069f9496d409d29c2e30393d1e3da46423e8a3c5",
        "sha256_in_prefix": "4311ec3170d832b72293da5d069f9496d409d29c2e30393d1e3da46423e8a3c5",
        "size_in_bytes": 593
      },
      {
        "_path": "lib/python3.6/site-packages/yaml/__pycache__/composer.cpython-36.pyc",
        "path_type": "hardlink",
        "sha256": "23182cd0d76e21e08283e8fd76f982a26f343c4c5b59ee10c99e024e87f026cc",
        "sha256_in_prefix": "23182cd0d76e21e08283e8fd76f982a26f343c4c5b59ee10c99e024e87f026cc",
        "size_in_bytes": 3524
      },
      {
        "_path": "lib/python3.6/site-packages/yaml/__pycache__/constructor.cpython-36.pyc",
        "path_type": "hardlink",
        "sha256": "67d52b3433588db18958f45e9b5f217bdb8858a62b6e1633f906d2dfa0f0a6d9",
        "sha256_in_prefix": "67d52b3433588db18958f45e9b5f217bdb8858a62b6e1633f906d2dfa0f0a6d9",
        "size_in_bytes": 21262
      },
      {
        "_path": "lib/python3.6/site-packages/yaml/__pycache__/cyaml.cpython-36.pyc",
        "path_type": "hardlink",
        "sha256": "1beefdb17f985a611e451ab6c6293ed1d7fbaec2e671d5839c82798852eb9d5a",
        "sha256_in_prefix": "1beefdb17f985a611e451ab6c6293ed1d7fbaec2e671d5839c82798852eb9d5a",
        "size_in_bytes": 3694
      },
      {
        "_path": "lib/python3.6/site-packages/yaml/__pycache__/dumper.cpython-36.pyc",
        "path_type": "hardlink",
        "sha256": "ceabf8bc9facbcf110daa0ba77acb61de50840bb06fa78354d884840c62acbe1",
        "sha256_in_prefix": "ceabf8bc9facbcf110daa0ba77acb61de50840bb06fa78354d884840c62acbe1",
        "size_in_bytes": 2064
      },
      {
        "_path": "lib/python3.6/site-packages/yaml/__pycache__/emitter.cpython-36.pyc",
        "path_type": "hardlink",
        "sha256": "0ab344472a344f3add1b4782614f5e27f32a7fb3d2c734eda687b81b184677d9",
        "sha256_in_prefix": "0ab344472a344f3add1b4782614f5e27f32a7fb3d2c734eda687b81b184677d9",
        "size_in_bytes": 25406
      },
      {
        "_path": "lib/python3.6/site-packages/yaml/__pycache__/error.cpython-36.pyc",
        "path_type": "hardlink",
        "sha256": "74a956656aceda62ee10b152fe605f8d1b41f9ec6b57e557e52726789149ab93",
        "sha256_in_prefix": "74a956656aceda62ee10b152fe605f8d1b41f9ec6b57e557e52726789149ab93",
        "size_in_bytes": 2275
      },
      {
        "_path": "lib/python3.6/site-packages/yaml/__pycache__/events.cpython-36.pyc",
        "path_type": "hardlink",
        "sha256": "edd5344302222996ae949cb0d600ae27d5399fc14a0070b6b7ceb02f56f56185",
        "sha256_in_prefix": "edd5344302222996ae949cb0d600ae27d5399fc14a0070b6b7ceb02f56f56185",
        "size_in_bytes": 4061
      },
      {
        "_path": "lib/python3.6/site-packages/yaml/__pycache__/loader.cpython-36.pyc",
        "path_type": "hardlink",
        "sha256": "e2aee14d04b1d23755f1f7c8d8e2aa3555ce33dea0a40baabd7dfe2fc55a0022",
        "sha256_in_prefix": "e2aee14d04b1d23755f1f7c8d8e2aa3555ce33dea0a40baabd7dfe2fc55a0022",
        "size_in_bytes": 2273
      },
      {
        "_path": "lib/python3.6/site-packages/yaml/__pycache__/nodes.cpython-36.pyc",
        "path_type": "hardlink",
        "sha256": "12aee62acc8e9329873d4a3ae5b83724704a4f0b20457ce028f9d5aeb4366d4d",
        "sha256_in_prefix": "12aee62acc8e9329873d4a3ae5b83724704a4f0b20457ce028f9d5aeb4366d4d",
        "size_in_bytes": 1719
      },
      {
        "_path": "lib/python3.6/site-packages/yaml/__pycache__/parser.cpython-36.pyc",
        "path_type": "hardlink",
        "sha256": "fc9951691e42ef1c5f81625a47d75134e71a7635d2ad60fdd0976fcb8900e567",
        "sha256_in_prefix": "fc9951691e42ef1c5f81625a47d75134e71a7635d2ad60fdd0976fcb8900e567",
        "size_in_bytes": 11895
      },
      {
        "_path": "lib/python3.6/site-packages/yaml/__pycache__/reader.cpython-36.pyc",
        "path_type": "hardlink",
        "sha256": "7ef2bd1d9ae18bf58a9d9e35589d63980ae8f50e084dae855128487f5cd6a9ab",
        "sha256_in_prefix": "7ef2bd1d9ae18bf58a9d9e35589d63980ae8f50e084dae855128487f5cd6a9ab",
        "size_in_bytes": 4484
      },
      {
        "_path": "lib/python3.6/site-packages/yaml/__pycache__/representer.cpython-36.pyc",
        "path_type": "hardlink",
        "sha256": "b18c52a09d66c6f26c1b9df07053df8080b945d56bab572779c2d826e92a05ab",
        "sha256_in_prefix": "b18c52a09d66c6f26c1b9df07053df8080b945d56bab572779c2d826e92a05ab",
        "size_in_bytes": 10120
      },
      {
        "_path": "lib/python3.6/site-packages/yaml/__pycache__/resolver.cpython-36.pyc",
        "path_type": "hardlink",
        "sha256": "953eb0dc24f821892cecac693239f7f675876f3dc8d511f643fb58bc042f3813",
        "sha256_in_prefix": "953eb0dc24f821892cecac693239f7f675876f3dc8d511f643fb58bc042f3813",
        "size_in_bytes": 5486
      },
      {
        "_path": "lib/python3.6/site-packages/yaml/__pycache__/scanner.cpython-36.pyc",
        "path_type": "hardlink",
        "sha256": "48834c79807d8a9d8adeda830e896f633118ff2fe457f3080a8be6c47e6e98c7",
        "sha256_in_prefix": "48834c79807d8a9d8adeda830e896f633118ff2fe457f3080a8be6c47e6e98c7",
        "size_in_bytes": 25869
      },
      {
        "_path": "lib/python3.6/site-packages/yaml/__pycache__/serializer.cpython-36.pyc",
        "path_type": "hardlink",
        "sha256": "41f3a7fe5904d63ba7a5cc1a4d024858b955cfa5442d62b30d664c54643bf829",
        "sha256_in_prefix": "41f3a7fe5904d63ba7a5cc1a4d024858b955cfa5442d62b30d664c54643bf829",
        "size_in_bytes": 3355
      },
      {
        "_path": "lib/python3.6/site-packages/yaml/__pycache__/tokens.cpython-36.pyc",
        "path_type": "hardlink",
        "sha256": "39af57003b08f3db3cd7e169992c32c99c5039a1aa23bb20b32fec3e45a6626b",
        "sha256_in_prefix": "39af57003b08f3db3cd7e169992c32c99c5039a1aa23bb20b32fec3e45a6626b",
        "size_in_bytes": 5218
      },
      {
        "_path": "lib/python3.6/site-packages/yaml/_yaml.cpython-36m-x86_64-linux-gnu.so",
        "path_type": "hardlink",
        "sha256": "d9741c991467666f67704a5a84b26c41b8a7b920437a52690bed657ef8982969",
        "sha256_in_prefix": "d9741c991467666f67704a5a84b26c41b8a7b920437a52690bed657ef8982969",
        "size_in_bytes": 296416
      },
      {
        "_path": "lib/python3.6/site-packages/yaml/_yaml.py",
        "path_type": "hardlink",
        "sha256": "dfd9569707308a50b938f8fe45c8437b6783bc8ab0c07e003626c262a901b4a5",
        "sha256_in_prefix": "dfd9569707308a50b938f8fe45c8437b6783bc8ab0c07e003626c262a901b4a5",
        "size_in_bytes": 431
      },
      {
        "_path": "lib/python3.6/site-packages/yaml/composer.py",
        "path_type": "hardlink",
        "sha256": "fcaa37d16afa783594794a5ab94193dcb720f503c19ce3d59539c8311189f453",
        "sha256_in_prefix": "fcaa37d16afa783594794a5ab94193dcb720f503c19ce3d59539c8311189f453",
        "size_in_bytes": 4883
      },
      {
        "_path": "lib/python3.6/site-packages/yaml/constructor.py",
        "path_type": "hardlink",
        "sha256": "90d8247da78b524c10618fd0e857f54f3d97570fe91b5c5513d024ef3faf88b0",
        "sha256_in_prefix": "90d8247da78b524c10618fd0e857f54f3d97570fe91b5c5513d024ef3faf88b0",
        "size_in_bytes": 28639
      },
      {
        "_path": "lib/python3.6/site-packages/yaml/cyaml.py",
        "path_type": "hardlink",
        "sha256": "e99ac01bd7c062f7557b614aff0d21997a06ed962ca185306a91bc0a20bbd87d",
        "sha256_in_prefix": "e99ac01bd7c062f7557b614aff0d21997a06ed962ca185306a91bc0a20bbd87d",
        "size_in_bytes": 3851
      },
      {
        "_path": "lib/python3.6/site-packages/yaml/dumper.py",
        "path_type": "hardlink",
        "sha256": "3cb72d66563064ba7b5e679477046ebf89d8399d940670c8532f3e94a7cb17ea",
        "sha256_in_prefix": "3cb72d66563064ba7b5e679477046ebf89d8399d940670c8532f3e94a7cb17ea",
        "size_in_bytes": 2837
      },
      {
        "_path": "lib/python3.6/site-packages/yaml/emitter.py",
        "path_type": "hardlink",
        "sha256": "8e086d694ede170837d5b1b407b45979aff6f40762f422a65eafd08e04290a44",
        "sha256_in_prefix": "8e086d694ede170837d5b1b407b45979aff6f40762f422a65eafd08e04290a44",
        "size_in_bytes": 43006
      },
      {
        "_path": "lib/python3.6/site-packages/yaml/error.py",
        "path_type": "hardlink",
        "sha256": "021f73fada072546c4f63f8cf18a7181244ce4280b09cc15cc980b2d1176171a",
        "sha256_in_prefix": "021f73fada072546c4f63f8cf18a7181244ce4280b09cc15cc980b2d1176171a",
        "size_in_bytes": 2533
      },
      {
        "_path": "lib/python3.6/site-packages/yaml/events.py",
        "path_type": "hardlink",
        "sha256": "e74fd392c810884e2ea7e94aa3f57e9c1cbeb402319083d0c58e6a0e1282787c",
        "sha256_in_prefix": "e74fd392c810884e2ea7e94aa3f57e9c1cbeb402319083d0c58e6a0e1282787c",
        "size_in_bytes": 2445
      },
      {
        "_path": "lib/python3.6/site-packages/yaml/loader.py",
        "path_type": "hardlink",
        "sha256": "5156becc8aa6905482218abf3e04869b835226db4763645fff3438fdbd5f1cdd",
        "sha256_in_prefix": "5156becc8aa6905482218abf3e04869b835226db4763645fff3438fdbd5f1cdd",
        "size_in_bytes": 2061
      },
      {
        "_path": "lib/python3.6/site-packages/yaml/nodes.py",
        "path_type": "hardlink",
        "sha256": "80f28d8fca4a09d87677882bde021820d9cf39a3b11a12405226211919cf13ce",
        "sha256_in_prefix": "80f28d8fca4a09d87677882bde021820d9cf39a3b11a12405226211919cf13ce",
        "size_in_bytes": 1440
      },
      {
        "_path": "lib/python3.6/site-packages/yaml/parser.py",
        "path_type": "hardlink",
        "sha256": "8a55a9e6fbe0a07146cef3990c8b45a068c3e83e369e1959ad9ca30306b4a09a",
        "sha256_in_prefix": "8a55a9e6fbe0a07146cef3990c8b45a068c3e83e369e1959ad9ca30306b4a09a",
        "size_in_bytes": 25495
      },
      {
        "_path": "lib/python3.6/site-packages/yaml/reader.py",
        "path_type": "hardlink",
        "sha256": "d1d9b38ab3a20c6e17a38d519ee412ecaf6b918df18c78956ac7c330d4ea08dc",
        "sha256_in_prefix": "d1d9b38ab3a20c6e17a38d519ee412ecaf6b918df18c78956ac7c330d4ea08dc",
        "size_in_bytes": 6794
      },
      {
        "_path": "lib/python3.6/site-packages/yaml/representer.py",
        "path_type": "hardlink",
        "sha256": "f3650cdd9c5440aaac28017896d58ec424ba8c63c816d5e91acee6beacafe17b",
        "sha256_in_prefix": "f3650cdd9c5440aaac28017896d58ec424ba8c63c816d5e91acee6beacafe17b",
        "size_in_bytes": 14184
      },
      {
        "_path": "lib/python3.6/site-packages/yaml/resolver.py",
        "path_type": "hardlink",
        "sha256": "6755bc00e300e8fae8cb88083b63a150ee083d2fdb14d025d026b7af00a1a4f8",
        "sha256_in_prefix": "6755bc00e300e8fae8cb88083b63a150ee083d2fdb14d025d026b7af00a1a4f8",
        "size_in_bytes": 8999
      },
      {
        "_path": "lib/python3.6/site-packages/yaml/scanner.py",
        "path_type": "hardlink",
        "sha256": "29e4082863654b23c4f100f08a89c7c72f4281ba84e6d789133d39151f7e9c08",
        "sha256_in_prefix": "29e4082863654b23c4f100f08a89c7c72f4281ba84e6d789133d39151f7e9c08",
        "size_in_bytes": 51277
      },
      {
        "_path": "lib/python3.6/site-packages/yaml/serializer.py",
        "path_type": "hardlink",
        "sha256": "0a1b85826854d35863e31808f0668abfabdf33606e8f06bd8bb7761401e3edc0",
        "sha256_in_prefix": "0a1b85826854d35863e31808f0668abfabdf33606e8f06bd8bb7761401e3edc0",
        "size_in_bytes": 4165
      },
      {
        "_path": "lib/python3.6/site-packages/yaml/tokens.py",
        "path_type": "hardlink",
        "sha256": "953408cd2570f0c83dc2fe39f7e4e388e41eeb05738aa69196a5f6ffcf6ba79e",
        "sha256_in_prefix": "953408cd2570f0c83dc2fe39f7e4e388e41eeb05738aa69196a5f6ffcf6ba79e",
        "size_in_bytes": 2573
      }
    ],
    "paths_version": 1
  },
  "requested_spec": "None",
  "sha256": "ecf74ae78a4b00bca99e1ab676ec4b511ff39f414416773855465ebb9e1b2bbb",
  "size": 173711,
  "subdir": "linux-64",
  "timestamp": 1611258435880,
  "track_features": "",
  "url": "https://repo.anaconda.com/pkgs/main/linux-64/pyyaml-5.4.1-py36h27cfd23_1.conda",
  "version": "5.4.1"
}